{
  "lpa_name": "Islington",
  "pp_id": null,
  "description": "Tree felling in the East Canonbury Conservation Area\r\nNotification has been received to carry out the following tree works:\r\nX1 Tree of Heaven - Fell",
  "epc_number": null,
  "status": "Insufficient Fee",
  "decision_date": null,
  "street_name": "Crowland Terrace",
  "decision_process": "Delegated",
  "uprn": "5300026112",
  "reference_no_of_permission_being_relied_on": null,
  "decision_target_date": "09/11/2010",
  "subdivision_of_building": null,
  "title_number": null,
  "date_building_work_completed_under_previous_permission": null,
  "centroid_easting": 532573,
  "appeal_decision": null,
  "lpa_app_no": "T100372",
  "development_type": null,
  "date_building_work_started_under_previous_permission": null,
  "polygon": null,
  "actual_commencement_date": null,
  "application_type": "All Other",
  "bo_system": "Agile APAS",
  "centroid": {
    "lat": 51.543105,
    "lon": -0.089643
  },
  "decision_agency": null,
  "parking_details": null,
  "postcode": "N1 3LP",
  "last_updated": "2025-03-20T01:49:19.398+00:00",
  "secondary_street_name": null,
  "cil_liability": false,
  "url_planning_app": null,
  "valid_date": "28/09/2010",
  "appeal_decision_date": null,
  "locality": "London",
  "appeal_start_date": null,
  "application_type_full": null,
  "decision": "Comment Issued",
  "last_updated_by": "Agile APAS",
  "actual_completion_date": null,
  "site_name": "",
  "lapsed_date": "12/10/2013",
  "centroid_northing": 184419,
  "decision_conditions": null,
  "ward": "East Acton",
  "site_number": "1",
  "application_details": {
    "s106_agreement": false
  },
  "id": "Islington-T100372",
  "appeal_status": null,
  "wgs84_polygon": {
    "type": "Polygon",
    "coordinates": [
      [
        [
          -0.089621,
          51.543118
        ],
        [
          -0.089622,
          51.543091
        ],
        [
          -0.089665,
          51.543092
        ],
        [
          -0.089664,
          51.543119
        ],
        [
          -0.089621,
          51.543118
        ]
      ]
    ]
  },
  "borough": "Islington",
  "last_date_consultation_comments": null
}