{
  "appeal_status": null,
  "centroid": {
    "lon": "-0.07762949999999999",
    "lat": "51.5421372"
  },
  "decision_target_date": "08/05/2023",
  "lapsed_date": "09/05/2026",
  "appeal_start_date": null,
  "last_updated": "2025-03-19T04:17:24.007+00:00",
  "locality": "HACKNEY",
  "development_type": "Minor dwellings",
  "postcode": "N1 4SD",
  "ward": "De Beauvoir Ward",
  "id": "Hackney-2023_0347",
  "uprn": "10008237615",
  "decision": "Approved",
  "site_name": "Flat 15, Dorset Court",
  "last_date_consultation_comments": "09/04/2023",
  "wgs84_polygon": {
    "coordinates": [
      [
        [
          -0.0776511,
          51.5421054,
          0
        ],
        [
          -0.07771299999999999,
          51.5421082,
          0
        ],
        [
          -0.07769609999999999,
          51.5421673,
          0
        ],
        [
          -0.0776429,
          51.5421638,
          0
        ],
        [
          -0.07753639999999999,
          51.5421566,
          0
        ],
        [
          -0.0775439,
          51.5421009,
          0
        ],
        [
          -0.0776511,
          51.5421054,
          0
        ]
      ]
    ],
    "type": "Polygon"
  },
  "actual_completion_date": null,
  "polygon": {
    "geometries": [
      {
        "coordinates": [
          [
            [
              533405.597106,
              184329.4213906,
              0
            ],
            [
              533401.2931116,
              184329.6215533,
              0
            ],
            [
              533402.2908314,
              184336.2295777,
              0
            ],
            [
              533405.9929243,
              184335.9294745,
              0
            ],
            [
              533413.3971111,
              184335.3292674,
              0
            ],
            [
              533413.042521,
              184329.1210943,
              0
            ],
            [
              533405.597106,
              184329.4213906,
              0
            ]
          ]
        ],
        "type": "Polygon"
      }
    ],
    "type": "GeometryCollection"
  },
  "date_building_work_started_under_previous_permission": null,
  "application_type_full": "Full planning permission",
  "title_number": null,
  "site_number": null,
  "lpa_name": "Hackney",
  "decision_process": "Delegated",
  "secondary_street_name": null,
  "street_name": "HERTFORD ROAD",
  "reference_no_of_permission_being_relied_on": null,
  "application_details": {
    "projected_cost_of_works": "Up to £2m",
    "total_gia_existing": 84.72,
    "scheme_phasing": true,
    "total_gia_gained": 0,
    "site_area": 0.007,
    "rain_water_harvesting": false,
    "non_residential_details": {
      "total_non_resi_gross_internal_floor_area_to_be_lost": 0,
      "total_gia_gained": 0,
      "total_non_resi_gross_internal_floor_area_to_be_gained": 0,
      "total_gia_lost": 0,
      "total_gia_existing": 84.72
    },
    "constraints_details": [
      {
        "result": null,
        "constraints_layer_description": "A4D De Beauvoir conservation area"
      },
      {
        "result": null,
        "constraints_layer_description": "A4D Storage and distribution to residential"
      },
      {
        "result": null,
        "constraints_layer_description": "Archaeological Priority Area"
      },
      {
        "result": null,
        "constraints_layer_description": "Controlled Parking Zone"
      },
      {
        "result": null,
        "constraints_layer_description": "Conservation Areas"
      },
      {
        "result": null,
        "constraints_layer_description": "CIL Zones"
      },
      {
        "result": null,
        "constraints_layer_description": "Crossrail Safeguarding"
      },
      {
        "result": null,
        "constraints_layer_description": "Aerodrome 3km consultation area"
      },
      {
        "result": "De Beauvoir",
        "constraints_layer_description": "Wards"
      },
      {
        "result": "Kingsland CAAC (ST)",
        "constraints_layer_description": "Consultees"
      },
      {
        "result": "2011/2036",
        "constraints_layer_description": "Application Boundaries"
      },
      {
        "result": "2011/2036",
        "constraints_layer_description": "Applications"
      }
    ],
    "garden_land_lost": false,
    "infrastructure_details": {
      "percentage_demolition_construction_material_recycling": 0,
      "no_non_resi_units_to_have_full_fibre": 0,
      "mobile_network_operators_consultation": false,
      "no_new_water_connections_required": 0,
      "total_annual_nox_emissions": 0,
      "ghg_reduction_over_building_regulations": false,
      "no_homes_passive_cooling": 0,
      "no_homes_to_have_electrical_heating": 0,
      "no_new_gas_connections_required": 0,
      "total_annual_pm_emissions": 0,
      "fire_suppression_system_proposed": false,
      "no_resi_units_to_have_full_fibre": 0,
      "green_roof_area": 0,
      "waste_provision": true
    },
    "ownership_status": "Private",
    "building_details": [
      {
        "no_storeys": 0,
        "max_height": 0,
        "building_ref": "0"
      }
    ],
    "total_gia_lost": 0,
    "phasing_details": [
      {
        "phase_detail": "Entire Development",
        "intended_completion_date": "06/2023",
        "intended_commencement_date": "05/2023"
      }
    ],
    "surface_water_discharge_percentage_reduction": 0,
    "internal_resi_water_usage": 0,
    "existing_proposed_floorspace_details": [
      {
        "gia_existing": 84.72,
        "use_class": "C3",
        "gia_gained": 0,
        "gia_lost": 0
      }
    ],
    "other_residential_accommodation_details": {
      "site_area": 84.72
    },
    "grey_water_reuse": false,
    "green_suds": false,
    "affordable_housing_fast_track": false
  },
  "valid_date": "13/03/2023",
  "parking_details": null,
  "actual_commencement_date": null,
  "centroid_northing": 184333,
  "application_type": "All Other",
  "decision_conditions": [
    "&lt;p&gt;Prior to the commencement of development, detailed drawings/full particulars of the proposed development showing the matters set out below must be submitted to and approved by the local planning authority, in writing. The development shall not be carried out otherwise than in accordance with the details thus approved.&lt;/p&gt;&lt;p&gt;a) 1:20 elevations and sections of the proposed door.&amp;nbsp;&lt;/p&gt;&lt;p&gt;b) materials details of the proposed door.&amp;nbsp;&amp;nbsp;&lt;/p&gt;&lt;p&gt;REASON: To ensure that the external appearance of the building is satisfactory and does not detract from the character and visual amenity of the area.&amp;nbsp;&lt;/p&gt;",
    "<p>The development hereby permitted must be begun not later than the expiration of three years beginning with the date of this permission.</p><p><br></p><p>\r\n</p><p>\r\nREASON: In order to comply with the provisions of the Town and Country Planning Act 1990 (as amended).</p><p>\r\n</p>",
    "&lt;p&gt;The development hereby permitted shall only be carried out and completed strictly in accordance with the submitted plans hereby approved and any subsequent approval of details.\r\n&lt;/p&gt;&lt;p&gt;&lt;br&gt;&lt;/p&gt;&lt;p&gt;\r\nREASON: To ensure that the development hereby permitted is carried out in full accordance with the plans hereby approved.\r\n&lt;/p&gt;"
  ],
  "url_planning_app": "/planning/index.html?fa=getApplication&id=75825",
  "pp_id": "11924843",
  "last_updated_by": "Planning Portal ingest",
  "centroid_easting": 533407,
  "borough": "Hackney",
  "epc_number": "2594-4146-5331-7764-6509",
  "lpa_app_no": "2023/0347",
  "decision_agency": "Borough",
  "date_building_work_completed_under_previous_permission": null,
  "bo_system": "Idox Tascomi",
  "subdivision_of_building": "Flat 15",
  "description": "Proposed works: Installation of double doors on the rear elevation.",
  "appeal_decision": null,
  "appeal_decision_date": null,
  "status": "Approved",
  "decision_date": "09/05/2023",
  "cil_liability": null
}