{
  "valid_date": "02/12/2024",
  "epc_number": null,
  "site_name": null,
  "cil_liability": false,
  "polygon": {
    "type": "GeometryCollection",
    "geometries": [
      {
        "coordinates": [
          [
            [
              523446.1000096,
              175222.0503286
            ],
            [
              523446.2500096,
              175217.6503286
            ],
            [
              523446.4500096,
              175212.1003286
            ],
            [
              523446.7000096,
              175203.3503286
            ],
            [
              523446.8000096,
              175200.1003286
            ],
            [
              523446.9000096,
              175197.6003286
            ],
            [
              523447.0000096,
              175193.5503286
            ],
            [
              523447.2500096,
              175186.6503286
            ],
            [
              523447.5000096,
              175179.7003286
            ],
            [
              523447.7000096,
              175172.9503286
            ],
            [
              523447.7500096,
              175171.8003286
            ],
            [
              523447.0500096,
              175171.8003286
            ],
            [
              523441.9500096,
              175171.9503286
            ],
            [
              523435.5500096,
              175172.1003286
            ],
            [
              523434.1000096,
              175217.1003286
            ],
            [
              523433.5500096,
              175228.5003286
            ],
            [
              523433.1000096,
              175238.7303286
            ],
            [
              523445.5500096,
              175237.5503286
            ],
            [
              523446.1000096,
              175222.0503286
            ]
          ]
        ],
        "type": "Polygon"
      }
    ]
  },
  "actual_commencement_date": null,
  "site_number": "253",
  "decision": "Approved",
  "parking_details": null,
  "application_type_full": "Tree works: Trees in conservation areas/subject to TPOs",
  "ward": "West Putney",
  "last_date_consultation_comments": "02/12/2024",
  "centroid_easting": "523438",
  "appeal_decision_date": null,
  "appeal_status": null,
  "description": "T1-Sycamore:Fell and  replace with a mature Magnolia grandiflora of 14/16cm girth and 4m height Evergreen species.",
  "appeal_decision": null,
  "postcode": "SW15 6SW",
  "date_building_work_completed_under_previous_permission": null,
  "decision_target_date": "13/01/2025",
  "street_name": "Upper Richmond Road",
  "decision_process": null,
  "last_updated_by": "Planning Portal ingest",
  "centroid_northing": "175222",
  "application_type": "All Other",
  "title_number": null,
  "decision_conditions": null,
  "appeal_start_date": null,
  "development_type": "Trees",
  "wgs84_polygon": {
    "coordinates": [
      [
        [
          -0.22437749999999998,
          51.462519
        ],
        [
          -0.2243769,
          51.4624794
        ],
        [
          -0.2243759,
          51.4624295
        ],
        [
          -0.2243754,
          51.4623508
        ],
        [
          -0.2243751,
          51.4623216
        ],
        [
          -0.22437449999999998,
          51.4622991
        ],
        [
          -0.22437449999999998,
          51.4622627
        ],
        [
          -0.2243733,
          51.4622006
        ],
        [
          -0.2243721,
          51.4621381
        ],
        [
          -0.22437159999999998,
          51.4620774
        ],
        [
          -0.2243713,
          51.462067
        ],
        [
          -0.22438139999999998,
          51.4620672
        ],
        [
          -0.22445469999999998,
          51.4620696
        ],
        [
          -0.2245467,
          51.4620724
        ],
        [
          -0.2245519,
          51.4624771
        ],
        [
          -0.2245558,
          51.4625797
        ],
        [
          -0.2245587,
          51.4626718
        ],
        [
          -0.22438000000000002,
          51.4626584
        ],
        [
          -0.22437749999999998,
          51.462519
        ]
      ]
    ],
    "type": "Polygon"
  },
  "lpa_app_no": "2024/4189",
  "decision_agency": "Borough",
  "decision_date": "22/01/2025",
  "pp_id": "13605381",
  "url_planning_app": "http://planning.wandsworth.gov.uk/Northgate/PlanningExplorer/DisplayAppDetails.aspx?AppNo=2024/4189",
  "lpa_name": "Wandsworth",
  "bo_system": "Northgate M3",
  "subdivision_of_building": null,
  "secondary_street_name": null,
  "date_building_work_started_under_previous_permission": null,
  "centroid": {
    "lat": "51.4625203",
    "lon": "-0.2244941"
  },
  "status": "Approved",
  "last_updated": "2025-03-19T19:36:55.135+00:00",
  "actual_completion_date": null,
  "lapsed_date": "22/01/2028",
  "borough": "Wandsworth",
  "id": "Wandsworth-2024_4189",
  "reference_no_of_permission_being_relied_on": null,
  "uprn": "121003285",
  "locality": "London",
  "application_details": {
    "site_area": 0.081
  }
}