{
  "polygon": {
    "type": "geometrycollection",
    "geometries": [
      {
        "coordinates": [
          [
            [
              525551.7009080059,
              166941.35311229003
            ],
            [
              525555.897644109,
              166944.552196562
            ],
            [
              525556.5737391197,
              166945.84182741056
            ],
            [
              525556.5490039364,
              166946.7715612761
            ],
            [
              525555.4441657482,
              166950.040625518
            ],
            [
              525554.1909164601,
              166951.79012472992
            ],
            [
              525555.9965848423,
              166953.1497355454
            ],
            [
              525542.6973012786,
              166967.6955718475
            ],
            [
              525538.5005651757,
              166970.95463894913
            ],
            [
              525533.4463427175,
              166964.74641603447
            ],
            [
              525544.700851127,
              166950.55047957494
            ],
            [
              525549.0459983299,
              166944.85211071384
            ],
            [
              525551.7009080059,
              166941.35311229003
            ]
          ]
        ],
        "type": "Polygon"
      }
    ]
  },
  "reference_no_of_permission_being_relied_on": null,
  "pp_id": "PP-09832215",
  "appeal_status": null,
  "last_updated": "2025-03-20T16:24:54.131+00:00",
  "appeal_decision_date": null,
  "status": "Refused",
  "decision_process": null,
  "epc_number": null,
  "last_date_consultation_comments": "17/06/2021",
  "secondary_street_name": null,
  "appeal_start_date": null,
  "ward": "St Helier_histroic",
  "centroid": {
    "lat": 51.387715,
    "lon": -0.197089
  },
  "decision": "Refused",
  "valid_date": "12/05/2021",
  "appeal_decision": null,
  "application_type_full": null,
  "development_type": "Minor all other minor developments",
  "locality": "Morden",
  "borough": "Merton",
  "last_updated_by": "Northgate M3",
  "actual_completion_date": null,
  "decision_agency": "Borough",
  "actual_commencement_date": null,
  "application_details": {
    "site_area": 0.028
  },
  "cil_liability": false,
  "postcode": "SM4 6LW",
  "title_number": null,
  "url_planning_app": "http://planning.merton.gov.uk/Northgate/PlanningExplorer/DisplayAppDetails.aspx?AppNo=21/P1806",
  "lpa_name": "Merton",
  "site_name": null,
  "lapsed_date": "22/06/2024",
  "parking_details": null,
  "decision_conditions": [
    "Reason : 1 - This application cannot be considered under the prior approval process as the proposed works are shown to extend beyond the rear of a wall that was not the rear wall of the original dwelling house. Therefore the proposal does not comply with Class A.1 (g) (i) of Part 1 of Schedule 2 of the Town and Country Planning (General Permitted Development) (England) Order 2015."
  ],
  "bo_system": "Northgate M3",
  "site_number": "10",
  "description": "APPLICATION FOR PRIOR APPROVAL IN RESPECT OF THE PROPOSED ERECTION OF A SINGLE STOREY REAR EXTENSION WITH THE FOLLOWING DIMENSIONS: \r\n\r\nEXTENDS BEYOND THE REAR WALL OF THE ORIGINAL DWELLINGHOUSE BY 6M \r\n\r\nTHE MAXIMUM HEIGHT OF THE ENLARGED PART OF THE DWELLINGHOUSE WILL BE 3.2M \r\n\r\nTHE HEIGHT OF THE EAVES OF THE ENLARGED PART OF THE DWELLINGHOUSE WILL BE 3M ",
  "lpa_app_no": "21/P1806",
  "decision_target_date": "22/06/2021",
  "date_building_work_started_under_previous_permission": null,
  "uprn": "48028456",
  "decision_date": "22/06/2021",
  "id": "Merton-21_P1806",
  "centroid_northing": 166950,
  "application_type": "Prior Approval",
  "subdivision_of_building": null,
  "date_building_work_completed_under_previous_permission": null,
  "centroid_easting": 525548,
  "street_name": "Garendon Gardens",
  "wgs84_polygon": {
    "coordinates": [
      [
        [
          -0.197039,
          51.387636
        ],
        [
          -0.196977,
          51.387664
        ],
        [
          -0.196967,
          51.387676
        ],
        [
          -0.196967,
          51.387684
        ],
        [
          -0.196982,
          51.387714
        ],
        [
          -0.196999,
          51.38773
        ],
        [
          -0.196973,
          51.387742
        ],
        [
          -0.197159,
          51.387875
        ],
        [
          -0.197218,
          51.387905
        ],
        [
          -0.197292,
          51.387851
        ],
        [
          -0.197136,
          51.387721
        ],
        [
          -0.197075,
          51.387669
        ],
        [
          -0.197039,
          51.387636
        ]
      ]
    ],
    "type": "Polygon"
  }
}