{
  "centroid_northing": "176029",
  "status": "Approved",
  "cil_liability": false,
  "appeal_decision_date": null,
  "centroid_easting": "532869",
  "application_type_full": null,
  "application_details": {
    "site_area": 0.226
  },
  "valid_date": "24/12/2021",
  "lpa_app_no": "21/AP/4713",
  "bo_system": "Idox Uniform",
  "application_type": "All Other",
  "last_updated": "2025-03-19T12:51:23.963+00:00",
  "decision_conditions": [
    "LB materials to match existing",
    "Standard time limit - LB and CAC consent"
  ],
  "decision": "Approved",
  "id": "Southwark-21_AP_4713",
  "description": "- Full repointing of tower masonry in like for like lime mortar as approved previously under  15/AP/3784\r- Minor brickwork repairs\r- Washing down brickwork to remove moss\r- Patch lime render repairs and stonework pinning",
  "lapsed_date": "10/02/2025",
  "actual_commencement_date": null,
  "date_building_work_completed_under_previous_permission": null,
  "site_name": "William Booth Memorial Training College\rChampion Park\rLondon\rSouthwark\rSE5 8BQ\r",
  "street_name": null,
  "parking_details": null,
  "locality": null,
  "polygon": {
    "geometries": [
      {
        "coordinates": [
          [
            [
              532902,
              176047
            ],
            [
              532894,
              176067
            ],
            [
              532892,
              176070
            ],
            [
              532890,
              176069
            ],
            [
              532889,
              176069
            ],
            [
              532890,
              176067
            ],
            [
              532889,
              176067
            ],
            [
              532887,
              176066
            ],
            [
              532886,
              176066
            ],
            [
              532883,
              176064
            ],
            [
              532883,
              176062
            ],
            [
              532887,
              176053
            ],
            [
              532869,
              176045
            ],
            [
              532868,
              176045
            ],
            [
              532867,
              176047
            ],
            [
              532866,
              176051
            ],
            [
              532856,
              176047
            ],
            [
              532857,
              176042
            ],
            [
              532858,
              176041
            ],
            [
              532857,
              176040
            ],
            [
              532839,
              176032
            ],
            [
              532835,
              176042
            ],
            [
              532834,
              176044
            ],
            [
              532831,
              176042
            ],
            [
              532830,
              176042
            ],
            [
              532828,
              176041
            ],
            [
              532827,
              176042
            ],
            [
              532826,
              176042
            ],
            [
              532823,
              176041
            ],
            [
              532825,
              176037
            ],
            [
              532833,
              176017
            ],
            [
              532845,
              176022
            ],
            [
              532846,
              176023
            ],
            [
              532849,
              176024
            ],
            [
              532850,
              176021
            ],
            [
              532852,
              176016
            ],
            [
              532861,
              176020
            ],
            [
              532862,
              176016
            ],
            [
              532864,
              176012
            ],
            [
              532866,
              176012
            ],
            [
              532871,
              176000
            ],
            [
              532873,
              175996
            ],
            [
              532874,
              175993
            ],
            [
              532876,
              175989
            ],
            [
              532876,
              175988
            ],
            [
              532893,
              175996
            ],
            [
              532891,
              176000
            ],
            [
              532889,
              176004
            ],
            [
              532883,
              176020
            ],
            [
              532885,
              176020
            ],
            [
              532883,
              176025
            ],
            [
              532882,
              176027
            ],
            [
              532882,
              176028
            ],
            [
              532889,
              176032
            ],
            [
              532887,
              176036
            ],
            [
              532886,
              176040
            ],
            [
              532891,
              176042
            ],
            [
              532902,
              176047
            ]
          ]
        ],
        "type": "Polygon"
      }
    ],
    "type": "GeometryCollection"
  },
  "development_type": null,
  "appeal_status": null,
  "reference_no_of_permission_being_relied_on": null,
  "decision_process": "Delegated",
  "epc_number": null,
  "decision_date": "10/02/2022",
  "site_number": null,
  "date_building_work_started_under_previous_permission": null,
  "centroid": {
    "lat": "51.4676396",
    "lon": "-0.0885092"
  },
  "borough": "London Borough of Southwark",
  "decision_agency": null,
  "appeal_decision": null,
  "appeal_start_date": null,
  "decision_target_date": "17/02/2022",
  "subdivision_of_building": null,
  "title_number": [],
  "url_planning_app": null,
  "secondary_street_name": null,
  "uprn": "010009796893",
  "postcode": null,
  "ward": "CHHI",
  "actual_completion_date": null,
  "last_updated_by": "Idox Uniform",
  "pp_id": "2166-A",
  "lpa_name": "Southwark",
  "last_date_consultation_comments": null,
  "wgs84_polygon": {
    "coordinates": [
      [
        [
          -0.0880276,
          51.4677936
        ],
        [
          -0.0881352,
          51.4679752
        ],
        [
          -0.0881629,
          51.4680027
        ],
        [
          -0.08819199999999999,
          51.4679941
        ],
        [
          -0.08820639999999999,
          51.4679944
        ],
        [
          -0.0881928,
          51.4679762
        ],
        [
          -0.0882072,
          51.4679764
        ],
        [
          -0.08823629999999999,
          51.4679679
        ],
        [
          -0.0882507,
          51.4679681
        ],
        [
          -0.0882946,
          51.4679509
        ],
        [
          -0.0882954,
          51.4679329
        ],
        [
          -0.08824119999999999,
          51.4678511
        ],
        [
          -0.08850319999999999,
          51.4677834
        ],
        [
          -0.0885176,
          51.4677836
        ],
        [
          -0.08853119999999999,
          51.4678018
        ],
        [
          -0.0885441,
          51.467838
        ],
        [
          -0.08868949999999999,
          51.4678044
        ],
        [
          -0.08867699999999999,
          51.4677593
        ],
        [
          -0.08866299999999999,
          51.46775
        ],
        [
          -0.0886777,
          51.4677413
        ],
        [
          -0.0889397,
          51.4676736
        ],
        [
          -0.08899349999999999,
          51.4677644
        ],
        [
          -0.08900709999999999,
          51.4677826
        ],
        [
          -0.0890511,
          51.4677654
        ],
        [
          -0.08906549999999999,
          51.4677656
        ],
        [
          -0.0890946,
          51.4677571
        ],
        [
          -0.0891086,
          51.4677663
        ],
        [
          -0.089123,
          51.4677665
        ],
        [
          -0.0891665,
          51.4677582
        ],
        [
          -0.08913929999999999,
          51.4677218
        ],
        [
          -0.08903169999999999,
          51.4675402
        ],
        [
          -0.0888571,
          51.4675823
        ],
        [
          -0.0888424,
          51.4675911
        ],
        [
          -0.0887988,
          51.4675994
        ],
        [
          -0.08878559999999999,
          51.4675722
        ],
        [
          -0.0887587,
          51.4675268
        ],
        [
          -0.08862769999999999,
          51.4675606
        ],
        [
          -0.0886148,
          51.4675244
        ],
        [
          -0.0885875,
          51.467488
        ],
        [
          -0.08855869999999999,
          51.4674875
        ],
        [
          -0.0884913,
          51.4673785
        ],
        [
          -0.088464,
          51.4673421
        ],
        [
          -0.0884508,
          51.4673149
        ],
        [
          -0.0884235,
          51.4672785
        ],
        [
          -0.0884239,
          51.4672695
        ],
        [
          -0.0881763,
          51.4673374
        ],
        [
          -0.0882036,
          51.4673738
        ],
        [
          -0.0882308,
          51.4674102
        ],
        [
          -0.08831119999999999,
          51.4675554
        ],
        [
          -0.0882824,
          51.467555
        ],
        [
          -0.0883093,
          51.4676004
        ],
        [
          -0.0883229,
          51.4676186
        ],
        [
          -0.0883225,
          51.4676276
        ],
        [
          -0.0882203,
          51.4676619
        ],
        [
          -0.0882476,
          51.4676983
        ],
        [
          -0.08826049999999999,
          51.4677345
        ],
        [
          -0.0881878,
          51.4677513
        ],
        [
          -0.0880276,
          51.4677936
        ]
      ]
    ],
    "type": "Polygon"
  }
}