{
  "actual_completion_date": null,
  "centroid_northing": 191643,
  "decision": "Approved",
  "development_type": null,
  "valid_date": "15/07/2021",
  "bo_system": "Agile APAS",
  "description": "Formation of a vehicular access and alterations to a driveway. (Summary).",
  "decision_conditions": [
    "The development hereby permitted shall be begun no later than the  expiration of three years from the date of this permission.\r\n\r\nReason: In order to comply with the requirements of Section 91 of the Town and Country Planning Act 1990."
  ],
  "appeal_status": null,
  "parking_details": {},
  "decision_process": "Delegated",
  "site_number": "227",
  "decision_target_date": "08/09/2021",
  "ward": "Hainault",
  "application_details": {
    "existing_uprns": null,
    "lead_developer_company_name": "Highways and Cleansing",
    "site_area": 0.023
  },
  "status": "Closed",
  "reference_no_of_permission_being_relied_on": null,
  "pp_id": "PP-09966446         ",
  "subdivision_of_building": null,
  "secondary_street_name": null,
  "application_type_full": null,
  "appeal_start_date": null,
  "lpa_name": "Redbridge",
  "borough": "Redbridge",
  "actual_commencement_date": null,
  "appeal_decision": null,
  "locality": "Hainault",
  "last_date_consultation_comments": "14/09/2021",
  "decision_date": "03/09/2021",
  "centroid": {
    "lon": "0.0963091",
    "lat": "51.6048945"
  },
  "date_building_work_completed_under_previous_permission": null,
  "epc_number": null,
  "url_planning_app": null,
  "street_name": "New North Road",
  "lpa_app_no": "2987/21",
  "lapsed_date": "03/09/2024",
  "id": "Redbridge-2987_21",
  "title_number": null,
  "application_type": "All Other",
  "site_name": "227, New North Road, Hainault, Ilford, IG6 3AG",
  "date_building_work_started_under_previous_permission": null,
  "postcode": "IG6 3AG",
  "last_updated": "2025-03-20T12:36:50.928+00:00",
  "last_updated_by": "Agile APAS",
  "decision_agency": null,
  "uprn": "100022229043",
  "cil_liability": null,
  "centroid_easting": 545268,
  "polygon": {
    "geometries": [
      {
        "coordinates": [
          [
            [
              545270.35,
              191629.8
            ],
            [
              545267.3,
              191637.3
            ],
            [
              545258.1,
              191660.1
            ],
            [
              545263.6,
              191662.4
            ],
            [
              545272.85,
              191639.5
            ],
            [
              545275.85,
              191632.05
            ],
            [
              545278.1,
              191626.4
            ],
            [
              545272.65,
              191624.2
            ],
            [
              545270.35,
              191629.8
            ]
          ]
        ],
        "type": "Polygon"
      }
    ],
    "type": "GeometryCollection"
  },
  "appeal_decision_date": null,
  "wgs84_polygon": {
    "coordinates": [
      [
        [
          0.0963376,
          51.6047753
        ],
        [
          0.0962966,
          51.6048435
        ],
        [
          0.09617329999999999,
          51.6050508
        ],
        [
          0.0962537,
          51.60507
        ],
        [
          0.0963776,
          51.6048618
        ],
        [
          0.0964178,
          51.6047941
        ],
        [
          0.09644799999999999,
          51.6047428
        ],
        [
          0.09636839999999999,
          51.6047244
        ],
        [
          0.0963376,
          51.6047753
        ]
      ]
    ],
    "type": "Polygon"
  }
}