{
  "appeal_status": null,
  "centroid": {
    "lon": "-0.31311259999999996",
    "lat": "51.4130301"
  },
  "decision_target_date": "18/04/2023",
  "lapsed_date": "14/04/2026",
  "appeal_start_date": null,
  "last_updated": "2025-03-20T12:21:31.921+00:00",
  "locality": null,
  "development_type": null,
  "postcode": "KT1 4AS",
  "ward": "HPK",
  "id": "Richmond-23_T0172_TCA",
  "uprn": "100022288339",
  "decision": "No Objection to Proposal (OBS only)",
  "site_name": "",
  "last_date_consultation_comments": null,
  "wgs84_polygon": null,
  "actual_completion_date": null,
  "polygon": {
    "coordinates": [
      [
        [
          517417.7,
          169586.2
        ],
        [
          517414.8,
          169587.15
        ],
        [
          517410.6,
          169588.55
        ],
        [
          517409.15,
          169589.25
        ],
        [
          517408.1,
          169585.9
        ],
        [
          517406,
          169579.25
        ],
        [
          517405.75,
          169578.45
        ],
        [
          517405.025,
          169576.29
        ],
        [
          517404.421,
          169574.491
        ],
        [
          517400.8,
          169563.7
        ],
        [
          517399.4,
          169559.6
        ],
        [
          517406.05,
          169557.35
        ],
        [
          517408.05,
          169556.65
        ],
        [
          517408.343,
          169557.49
        ],
        [
          517408.8,
          169558.8
        ],
        [
          517412.45,
          169570.05
        ],
        [
          517414,
          169575.05
        ],
        [
          517414.512,
          169576.654
        ],
        [
          517416.6,
          169583.2
        ],
        [
          517417.7,
          169586.2
        ]
      ]
    ],
    "type": "Polygon"
  },
  "date_building_work_started_under_previous_permission": null,
  "application_type_full": "Tree works: Trees in conservation areas/subject to TPOs",
  "title_number": [],
  "site_number": "41",
  "lpa_name": "Richmond",
  "decision_process": "Delegated",
  "secondary_street_name": null,
  "street_name": "Park Road",
  "reference_no_of_permission_being_relied_on": null,
  "application_details": {
    "site_area": 0.028
  },
  "valid_date": "07/03/2023",
  "parking_details": null,
  "actual_commencement_date": null,
  "centroid_northing": 169573,
  "application_type": "All Other",
  "decision_conditions": [
    ""
  ],
  "url_planning_app": null,
  "pp_id": "PP-11984482",
  "last_updated_by": "Planning Portal ingest",
  "centroid_easting": 517409,
  "borough": "Richmond upon Thames",
  "epc_number": null,
  "lpa_app_no": "23/T0172/TCA",
  "decision_agency": null,
  "date_building_work_completed_under_previous_permission": null,
  "bo_system": "Idox Uniform",
  "subdivision_of_building": null,
  "description": "T1 - Prunus Nigra reduce by 1 meter and remove all deadwood this will leave the tree at a height of 4/5 meters tall and a canopy of 3 meters max- reasons - general maintenance.",
  "appeal_decision": null,
  "appeal_decision_date": null,
  "status": "No Objection to Proposal (OBS only)",
  "decision_date": "14/04/2023",
  "cil_liability": false
}