{
  "lpa_name": "Islington",
  "pp_id": null,
  "description": "Certificate of Lawfulness (proposed) in connection with partial demolition of rear lean to and the construction of a single storey rear extension.",
  "epc_number": null,
  "status": "Insufficient Fee",
  "decision_date": "13/03/2014",
  "street_name": "Highbury Hill",
  "decision_process": "Delegated",
  "uprn": "5300044251",
  "reference_no_of_permission_being_relied_on": null,
  "decision_target_date": "19/03/2014",
  "subdivision_of_building": null,
  "title_number": null,
  "date_building_work_completed_under_previous_permission": null,
  "centroid_easting": 531511,
  "appeal_decision": null,
  "lpa_app_no": "P2014/0303/COLP",
  "development_type": null,
  "date_building_work_started_under_previous_permission": null,
  "polygon": {
    "geometries": [
      {
        "coordinates": [
          [
            [
              531527.6469778,
              185902.9950725
            ],
            [
              531520.4407944,
              185898.1964461
            ],
            [
              531499.9930429,
              185884.750295
            ],
            [
              531492.1025194,
              185879.5017974
            ],
            [
              531489.5465505,
              185883.4506671
            ],
            [
              531489.348669,
              185883.7505812
            ],
            [
              531498.9459201,
              185890.3486925
            ],
            [
              531499.9930429,
              185890.8985351
            ],
            [
              531512.7976228,
              185899.4960741
            ],
            [
              531524.695246,
              185907.3538249
            ],
            [
              531528.8919821,
              185910.1030379
            ],
            [
              531529.0486382,
              185909.8031237
            ],
            [
              531531.7942436,
              185905.7542827
            ],
            [
              531527.6469778,
              185902.9950725
            ]
          ]
        ],
        "type": "Polygon"
      }
    ],
    "type": "GeometryCollection"
  },
  "actual_commencement_date": null,
  "application_type": "All Other",
  "bo_system": "Agile APAS",
  "centroid": {
    "lat": "51.5566193",
    "lon": "-0.1043707"
  },
  "decision_agency": null,
  "parking_details": null,
  "postcode": "N5 1AT",
  "last_updated": "2025-03-20T01:13:30.097+00:00",
  "secondary_street_name": null,
  "cil_liability": false,
  "url_planning_app": null,
  "valid_date": "22/01/2014",
  "appeal_decision_date": null,
  "locality": "London",
  "appeal_start_date": null,
  "application_type_full": null,
  "decision": "Approved",
  "last_updated_by": "Agile APAS",
  "actual_completion_date": null,
  "site_name": "",
  "lapsed_date": "13/03/2017",
  "centroid_northing": 185895,
  "decision_conditions": null,
  "ward": "College Park and Old Oak",
  "site_number": "128",
  "application_details": {
    "lead_developer_company_name": "Councillor Andy Hull",
    "s106_agreement": false,
    "site_area": 0.025
  },
  "id": "Islington-P2014_0303_COLP",
  "appeal_status": null,
  "wgs84_polygon": {
    "type": "Polygon",
    "coordinates": [
      [
        [
          -0.10412769999999999,
          51.5566873
        ],
        [
          -0.10423339999999999,
          51.5566458
        ],
        [
          -0.10453319999999999,
          51.5565298
        ],
        [
          -0.10464889999999999,
          51.5564844
        ],
        [
          -0.1046843,
          51.5565205
        ],
        [
          -0.10468699999999999,
          51.5565233
        ],
        [
          -0.10454619999999999,
          51.5565803
        ],
        [
          -0.1045309,
          51.556585
        ],
        [
          -0.1043431,
          51.5566593
        ],
        [
          -0.10416869999999999,
          51.5567271
        ],
        [
          -0.1041071,
          51.5567509
        ],
        [
          -0.10410499999999999,
          51.5567481
        ],
        [
          -0.10406689999999999,
          51.5567111
        ],
        [
          -0.10412769999999999,
          51.5566873
        ]
      ]
    ]
  },
  "borough": "Islington",
  "last_date_consultation_comments": null
}