{
  "polygon": {
    "geometries": [
      {
        "coordinates": [
          [
            [
              507280.5177,
              181620.8094
            ],
            [
              507281.8406,
              181626.6302
            ],
            [
              507288.4552,
              181625.0427
            ],
            [
              507289.249,
              181628.2177
            ],
            [
              507292.1594,
              181627.5563
            ],
            [
              507292.2917,
              181627.6886
            ],
            [
              507292.6886,
              181628.8792
            ],
            [
              507293.35,
              181628.7469
            ],
            [
              507293.4823,
              181628.7469
            ],
            [
              507295.3344,
              181631.2604
            ],
            [
              507307.7698,
              181628.4823
            ],
            [
              507310.8125,
              181629.0115
            ],
            [
              507313.0615,
              181625.175
            ],
            [
              507319.8084,
              181616.576
            ],
            [
              507308.5636,
              181618.6927
            ],
            [
              507308.299,
              181617.5021
            ],
            [
              507294.6729,
              181620.5448
            ],
            [
              507291.7625,
              181618.4281
            ],
            [
              507288.9844,
              181618.9573
            ],
            [
              507288.5875,
              181618.6927
            ],
            [
              507280.5177,
              181620.5448
            ],
            [
              507280.5177,
              181620.8094
            ]
          ]
        ],
        "type": "Polygon"
      }
    ],
    "type": "GeometryCollection"
  },
  "reference_no_of_permission_being_relied_on": null,
  "pp_id": null,
  "appeal_status": null,
  "last_updated": "2025-03-20T23:43:46.124+00:00",
  "appeal_decision_date": null,
  "status": "Refused",
  "decision_process": "Delegated",
  "epc_number": null,
  "last_date_consultation_comments": "25/03/2020",
  "secondary_street_name": "HILLINGDON",
  "appeal_start_date": null,
  "ward": "YIEWSLEY",
  "centroid": {
    "lat": "51.5233501",
    "lon": "-0.4547602"
  },
  "decision": "Refused",
  "valid_date": "02/03/2020",
  "appeal_decision": null,
  "application_type_full": null,
  "development_type": null,
  "locality": null,
  "borough": "Hillingdon",
  "last_updated_by": "CSV Data Import",
  "actual_completion_date": null,
  "decision_agency": "Borough",
  "actual_commencement_date": null,
  "application_details": {
    "existing_uprns": null,
    "site_area": 0.032
  },
  "cil_liability": false,
  "postcode": "UB8 3QL",
  "title_number": null,
  "url_planning_app": "http://planning.hillingdon.gov.uk/OcellaWeb/planningDetails?reference=75391/APP/2020/491",
  "lpa_name": "Hillingdon",
  "site_name": "2 MOORCROFT COTTAGES",
  "lapsed_date": "08/04/2023",
  "parking_details": null,
  "decision_conditions": [
    "The proposed development does not constitute permitted development by virtue of the provisions of Section 7 of the Planning (Listed Buildings and Conservation Areas) Act 1990 which states that, no person shall execute or cause to be executed any works for the demolition of a listed building or for its alteration or extension in any manner which would affect its character as a building of special architectural or historic interest, unless the works are authorised under Section 8 of said Act."
  ],
  "bo_system": "CSV Data Import",
  "site_number": null,
  "description": "Erection of a single storey rear extension, which would extend beyond the rear wall of the original house by 4 metres, for which the maximum height would be 2.9 metres, and for which the height of the eaves would be 2.9 metres",
  "lpa_app_no": "75391/APP/2020/491",
  "decision_target_date": "12/04/2020",
  "date_building_work_started_under_previous_permission": null,
  "uprn": null,
  "decision_date": "08/04/2020",
  "id": "Hillingdon-75391_APP_2020_491",
  "centroid_northing": 181624,
  "application_type": "Prior Approval",
  "subdivision_of_building": null,
  "date_building_work_completed_under_previous_permission": null,
  "centroid_easting": 507300,
  "street_name": "MOORCROFT LANE",
  "wgs84_polygon": {
    "coordinates": [
      [
        [
          -0.4550418,
          51.5233251
        ],
        [
          -0.45502099999999995,
          51.5233772
        ],
        [
          -0.4549262,
          51.5233616
        ],
        [
          -0.4549138,
          51.52339
        ],
        [
          -0.4548721,
          51.5233835
        ],
        [
          -0.4548701,
          51.5233847
        ],
        [
          -0.454864,
          51.5233953
        ],
        [
          -0.4548545,
          51.523394
        ],
        [
          -0.4548526,
          51.523394
        ],
        [
          -0.4548252,
          51.5234162
        ],
        [
          -0.45464689999999996,
          51.5233889
        ],
        [
          -0.4546029,
          51.5233931
        ],
        [
          -0.45457159999999996,
          51.5233582
        ],
        [
          -0.45447699999999996,
          51.5232796
        ],
        [
          -0.4546384,
          51.5233007
        ],
        [
          -0.45464259999999995,
          51.5232901
        ],
        [
          -0.45483799999999996,
          51.52332
        ],
        [
          -0.45488049999999997,
          51.523301599999996
        ],
        [
          -0.4549204,
          51.5233068
        ],
        [
          -0.4549262,
          51.5233045
        ],
        [
          -0.4550419,
          51.5233227
        ],
        [
          -0.4550418,
          51.5233251
        ]
      ]
    ],
    "type": "Polygon"
  }
}