{
  "cil_liability": false,
  "url_planning_app": null,
  "lapsed_date": "22/06/2023",
  "decision_target_date": "22/06/2020",
  "locality": null,
  "subdivision_of_building": null,
  "bo_system": "Idox Uniform",
  "lpa_name": "Hammersmith & Fulham",
  "postcode": "W6 0HA",
  "site_name": "",
  "status": "Appeal In Progress",
  "application_details": {
    "site_area": 0.015000000000000001
  },
  "appeal_decision_date": null,
  "lpa_app_no": "2020/01040/FUL",
  "date_building_work_started_under_previous_permission": null,
  "centroid_easting": 522720,
  "date_building_work_completed_under_previous_permission": null,
  "title_number": [],
  "application_type_full": null,
  "last_updated": "2025-03-20T20:50:27.254+00:00",
  "id": "Hammersmith_&_Fulham-2020_01040_FUL",
  "application_type": "All Other",
  "street_name": "Nasmyth Street",
  "borough": "London Borough of Hammersmith and Fulham",
  "ward": "RAVENS",
  "decision_date": "22/06/2020",
  "epc_number": null,
  "actual_commencement_date": null,
  "appeal_status": null,
  "appeal_start_date": null,
  "decision_process": "Delegated",
  "description": "Erection of a rear roof extension including the formation of a hip to gable roof extension; erection of a rear extension at second floor level, over part of the existing back addition; erection of a single storey extension to the side of the main building following the demolition of the existing garage; erection of a single storey rear extension; installation of 3no. rooflights in the front roofslope; alterations to the front and rear facades including replacement of existing windows.",
  "actual_completion_date": null,
  "last_date_consultation_comments": "19/05/2020",
  "last_updated_by": "Idox Uniform",
  "development_type": null,
  "centroid_northing": 179030,
  "decision": "Approved",
  "appeal_decision": null,
  "uprn": "000034012977",
  "centroid": {
    "lon": "-0.23350279999999998",
    "lat": "51.4969004"
  },
  "polygon": {
    "geometries": [
      {
        "coordinates": [
          [
            [
              522712.85,
              179025
            ],
            [
              522711.35,
              179024.95
            ],
            [
              522711.1,
              179027.8
            ],
            [
              522710.55,
              179033.05
            ],
            [
              522711.95,
              179033.2
            ],
            [
              522722.753,
              179034.49
            ],
            [
              522725.35,
              179034.8
            ],
            [
              522727.1,
              179034.95
            ],
            [
              522727.95,
              179035.05
            ],
            [
              522728.1,
              179030.2
            ],
            [
              522728.2,
              179025.4
            ],
            [
              522727.4,
              179025.4
            ],
            [
              522724.15,
              179025.3
            ],
            [
              522722.3,
              179025.25
            ],
            [
              522720.596,
              179025.158
            ],
            [
              522717.65,
              179025
            ],
            [
              522712.85,
              179025
            ]
          ]
        ],
        "type": "Polygon"
      }
    ],
    "type": "GeometryCollection"
  },
  "parking_details": null,
  "decision_agency": null,
  "decision_conditions": [
    "Expiry date",
    "No external changes",
    "No terrace",
    "External materials",
    "Slates",
    "No HMO",
    "FRA compliance",
    "1:20",
    "Justification",
    "In accordance",
    "Timber windows"
  ],
  "reference_no_of_permission_being_relied_on": null,
  "valid_date": "27/04/2020",
  "secondary_street_name": null,
  "site_number": "95",
  "pp_id": "PP-08675231",
  "wgs84_polygon": {
    "coordinates": [
      [
        [
          -0.2336075,
          51.496857
        ],
        [
          -0.23362909999999998,
          51.4968569
        ],
        [
          -0.2336317,
          51.4968826
        ],
        [
          -0.23363779999999998,
          51.4969299
        ],
        [
          -0.23361759999999998,
          51.4969309
        ],
        [
          -0.2334616,
          51.4969402
        ],
        [
          -0.2334241,
          51.4969424
        ],
        [
          -0.2333988,
          51.4969434
        ],
        [
          -0.2333866,
          51.4969441
        ],
        [
          -0.23338609999999999,
          51.4969005
        ],
        [
          -0.2333863,
          51.4968573
        ],
        [
          -0.2333978,
          51.4968575
        ],
        [
          -0.23344469999999998,
          51.4968573
        ],
        [
          -0.2334713,
          51.4968572
        ],
        [
          -0.23349589999999998,
          51.4968568
        ],
        [
          -0.23353839999999998,
          51.496856
        ],
        [
          -0.2336075,
          51.496857
        ]
      ]
    ],
    "type": "Polygon"
  }
}