{
  "borough": "Bromley Custodian Code",
  "cil_liability": false,
  "decision_target_date": "30/08/2023",
  "lpa_app_no": "23/02585/FULL6",
  "date_building_work_completed_under_previous_permission": null,
  "decision_date": "29/08/2023",
  "lpa_name": "Bromley",
  "application_details": {
    "intended_completion_date": "04/2024",
    "no_additional_bedrooms": 1,
    "intended_commencement_date": "01/2024",
    "total_gia_gained": 40,
    "no_additional_bathrooms": 1,
    "site_area": 0.039
  },
  "title_number": [],
  "wgs84_polygon": {
    "type": "Polygon",
    "coordinates": [
      [
        [
          0.0979034,
          51.4067159
        ],
        [
          0.0979012,
          51.4067146
        ],
        [
          0.09779499999999999,
          51.4067531
        ],
        [
          0.0977591,
          51.4067661
        ],
        [
          0.0974394,
          51.406882
        ],
        [
          0.0973367,
          51.4069163
        ],
        [
          0.0974336,
          51.4069766
        ],
        [
          0.0975462,
          51.4069381
        ],
        [
          0.0976488,
          51.406903
        ],
        [
          0.0976949,
          51.4068882
        ],
        [
          0.0977256,
          51.4068706
        ],
        [
          0.09776309999999999,
          51.4068542
        ],
        [
          0.09783109999999999,
          51.4068257
        ],
        [
          0.097979,
          51.406764
        ],
        [
          0.0979545,
          51.4067474
        ],
        [
          0.09792859999999999,
          51.4067321
        ],
        [
          0.0979034,
          51.4067159
        ]
      ]
    ]
  },
  "valid_date": "05/07/2023",
  "centroid": {
    "lat": "51.406847",
    "lon": "0.0976621"
  },
  "site_number": "10",
  "decision_conditions": [
    "Materials in Accordance with Plans",
    "Standard Time Limit",
    "Standard Compliance with Plans",
    ""
  ],
  "decision": "Approved",
  "centroid_easting": 545993,
  "uprn": "100020449583",
  "decision_process": "Delegated",
  "application_type_full": "Householder planning permission",
  "locality": null,
  "last_date_consultation_comments": null,
  "polygon": {
    "coordinates": [
      [
        [
          545985.7094986,
          169629.4662406
        ],
        [
          545985.725832,
          169626.4618367
        ],
        [
          545982.7323175,
          169626.4873554
        ],
        [
          545982.7159858,
          169629.4917594
        ],
        [
          545985.7094986,
          169629.4662406
        ]
      ]
    ],
    "type": "GeometryCollection",
    "geometries": [
      {
        "coordinates": [
          [
            [
              546010.2,
              169608.9
            ],
            [
              546010.05,
              169608.75
            ],
            [
              546002.54,
              169612.82
            ],
            [
              546000,
              169614.2
            ],
            [
              545977.4,
              169626.45
            ],
            [
              545970.15,
              169630.05
            ],
            [
              545976.7,
              169636.95
            ],
            [
              545984.65,
              169632.9
            ],
            [
              545991.9,
              169629.2
            ],
            [
              545995.149,
              169627.641
            ],
            [
              545997.34,
              169625.748
            ],
            [
              546000,
              169624
            ],
            [
              546004.82,
              169620.97
            ],
            [
              546015.3,
              169614.4
            ],
            [
              546013.65,
              169612.5
            ],
            [
              546011.9,
              169610.75
            ],
            [
              546010.2,
              169608.9
            ]
          ]
        ],
        "type": "Polygon"
      }
    ]
  },
  "ward": "STPAUC",
  "pp_id": "PP-12288007",
  "lapsed_date": "29/08/2026",
  "decision_agency": null,
  "actual_completion_date": null,
  "description": "Detached single storey bedroom annex at rear",
  "centroid_northing": 169623,
  "street_name": "Blythe Hill",
  "epc_number": null,
  "appeal_status": null,
  "appeal_decision": null,
  "secondary_street_name": null,
  "appeal_start_date": null,
  "status": "Approved",
  "reference_no_of_permission_being_relied_on": null,
  "last_updated": "2025-03-19T03:43:34.354+00:00",
  "site_name": "",
  "development_type": null,
  "appeal_decision_date": null,
  "last_updated_by": "Idox Uniform",
  "application_type": "Householder",
  "bo_system": "Idox Uniform",
  "subdivision_of_building": null,
  "parking_details": null,
  "date_building_work_started_under_previous_permission": null,
  "url_planning_app": null,
  "id": "Bromley-23_02585_FULL6",
  "actual_commencement_date": null,
  "postcode": "BR5 2RR"
}