{
  "centroid_easting": 544609,
  "reference_no_of_permission_being_relied_on": null,
  "lpa_name": "Bromley",
  "lpa_app_no": "23/02821/HHPA",
  "last_date_consultation_comments": null,
  "date_building_work_started_under_previous_permission": null,
  "appeal_decision": null,
  "bo_system": "Idox Uniform",
  "epc_number": null,
  "centroid": {
    "lat": "51.3693725",
    "lon": "0.0760656"
  },
  "postcode": "BR6 8AU",
  "actual_completion_date": null,
  "street_name": "Rusland Avenue",
  "borough": "Bromley Custodian Code",
  "wgs84_polygon": {
    "coordinates": [
      [
        [
          0.0760787,
          51.369218
        ],
        [
          0.0760441,
          51.3692146
        ],
        [
          0.07602579999999999,
          51.3692716
        ],
        [
          0.0760025,
          51.369343
        ],
        [
          0.07599979999999999,
          51.3693515
        ],
        [
          0.0759937,
          51.3693702
        ],
        [
          0.0759924,
          51.3693743
        ],
        [
          0.07595149999999999,
          51.3695035
        ],
        [
          0.0761046,
          51.3695206
        ],
        [
          0.076123,
          51.3694493
        ],
        [
          0.0761303,
          51.3694214
        ],
        [
          0.0761468,
          51.3693575
        ],
        [
          0.0761515,
          51.3693427
        ],
        [
          0.0761666,
          51.3692949
        ],
        [
          0.0761825,
          51.3692252
        ],
        [
          0.0761645,
          51.3692241
        ],
        [
          0.076158,
          51.3692238
        ],
        [
          0.076122,
          51.3692217
        ],
        [
          0.076114,
          51.369221
        ],
        [
          0.0760787,
          51.369218
        ]
      ]
    ],
    "type": "Polygon"
  },
  "url_planning_app": null,
  "appeal_decision_date": null,
  "cil_liability": false,
  "secondary_street_name": null,
  "id": "Bromley-23_02821_HHPA",
  "ward": "FARCRT",
  "title_number": [],
  "description": "Single storey rear extension, extending beyond the rear wall of the original house by 3.35m, for which the maximum height would be 2.9m, and for which the height of the eaves would be 2.75m (42 Day Notification for Householder Permitted Development Prior Approval)",
  "uprn": "100020473606",
  "site_name": "",
  "decision_agency": null,
  "centroid_northing": 165413,
  "application_details": {
    "site_area": 0.034
  },
  "date_building_work_completed_under_previous_permission": null,
  "decision_target_date": "31/08/2023",
  "subdivision_of_building": null,
  "decision_date": "21/08/2023",
  "decision": "Not Required",
  "locality": null,
  "appeal_start_date": null,
  "actual_commencement_date": null,
  "polygon": {
    "coordinates": [
      [
        [
          544607.6283989,
          165408.3464328
        ],
        [
          544607.6437123,
          165405.3420559
        ],
        [
          544604.6475851,
          165405.3685217
        ],
        [
          544604.6322735,
          165408.3728986
        ],
        [
          544607.6283989,
          165408.3464328
        ]
      ]
    ],
    "type": "GeometryCollection",
    "geometries": [
      {
        "coordinates": [
          [
            [
              544610.4,
              165395.85
            ],
            [
              544608,
              165395.4
            ],
            [
              544606.55,
              165401.7
            ],
            [
              544604.705,
              165409.601
            ],
            [
              544604.487,
              165410.535
            ],
            [
              544604.003,
              165412.606
            ],
            [
              544603.898,
              165413.063
            ],
            [
              544600.65,
              165427.35
            ],
            [
              544611.25,
              165429.55
            ],
            [
              544612.758,
              165421.659
            ],
            [
              544613.348,
              165418.572
            ],
            [
              544614.701,
              165411.494
            ],
            [
              544615.075,
              165409.854
            ],
            [
              544616.278,
              165404.571
            ],
            [
              544617.6,
              165396.85
            ],
            [
              544616.35,
              165396.7
            ],
            [
              544615.9,
              165396.65
            ],
            [
              544613.4,
              165396.35
            ],
            [
              544612.85,
              165396.25
            ],
            [
              544610.4,
              165395.85
            ]
          ]
        ],
        "type": "Polygon"
      }
    ]
  },
  "development_type": null,
  "lapsed_date": "21/08/2028",
  "application_type": "Prior Approval",
  "decision_conditions": null,
  "parking_details": null,
  "last_updated": "2025-03-20T12:23:26.652+00:00",
  "last_updated_by": "Idox Uniform",
  "site_number": "15",
  "appeal_status": null,
  "decision_process": null,
  "application_type_full": null,
  "valid_date": "20/07/2023",
  "pp_id": null,
  "status": "Approved"
}